model/mux.vhd
library IEEE;
use IEEE.std_logic_1164.all;
use IEEE.numeric_std.all;

entity MUX is
    port (
        s0, s1, s2, a0, a1, a2, a3, a4, a5, a6, a7 : in std_logic;
        z : out std_logic
    );
end entity MUX;

architecture arch of MUX is
    signal i0, i1, i2, i3, i4, i5, i6, i7 : std_logic;
begin
    process is begin
        wait on s0, s1, s2, a0, a1, a2, a3, a4, a5, a6, a7, i0, i1, i2, i3, i4, i5, i6, i7 ;
        i0 <= a0  and (not s0)  and  (not s1)  and  (not s2);
        i1 <= a1  and (not s0)  and  (not s1)  and       s2;             
        i2 <= a2  and (not s0)  and       s1   and  (not s2);
        i3 <= a3  and (not s0)  and       s1   and       s2;
        i4 <= a4  and      s0   and  (not s1)  and  (not s2);
        i5 <= a5  and      s0   and  (not s1)  and       s2;
        i6 <= a6  and      s0   and       s1   and  (not s2);
        i7 <= a7  and      s0   and       s1   and       s2;
        z <= i0 or i1 or i2 or i3 or i4 or i5 or i6 or i7;
    end process;
end architecture arch;

model/inc.vhd
library IEEE;
use IEEE.std_logic_1164.all;
use IEEE.numeric_std.all;

entity INC is
    port (
        s0, s1, s2, i0, i1 : in std_logic;
        k0, k1, c_out : out std_logic
    );
end entity INC;

architecture arch of INC is
    signal s_and, c : std_logic;
begin
    process is begin
        wait on s0, s1, s2, i0, i1, s_and, c;
        s_and <= s0 and s1 and s2;
        k1 <= s_and xor i1;
        c <= s_and and i1;
        k0 <= i0 xor c;
        c_out <= c and i0;
    end process;    
end architecture arch;

model/sub2.vhd
library IEEE;
use IEEE.std_logic_1164.all;
use IEEE.numeric_std.all;

entity SUB_2 is
    port (
        s0, s1, i0, i1, j0, j1 : in std_logic;
        k0, k1, c_out : out std_logic
    );
end entity SUB_2;

architecture arch of SUB_2 is
    signal j0_c, j1_c, s_and, c : std_logic;
begin
    process is begin
        wait on s0, s1, i0, i1, j0, j1, j0_c, j1_c, c;
        j1_c <= not j1;
        j0_c <= not j0;
        s_and <= s0 and s1;

        k1 <= (i1 xor j1_c) xor s_and;
        c <= (i1 and j1_c) or (s_and and (i1 xor j1_c));
        k0 <= (i0 xor j0_c) xor c;
        c_out <= (i0 and j0_c) or (c and (i0 xor j0_c));
    end process;
end architecture arch;

model/not.vhd
library IEEE;
use IEEE.std_logic_1164.all;
use IEEE.numeric_std.all;

entity NOT_OP is
    port (
        s0, i0, i1 : in std_logic;
        k0, k1, c_out: out std_logic
    );
end entity NOT_OP;

architecture arch of NOT_OP is
begin
    process is begin
        wait on i0, i1;
        k0 <= not i0;
        k1 <= not i1;
        c_out <= s0;
    end process;
end architecture arch;

model/xor.vhd
library IEEE;
use IEEE.std_logic_1164.all;
use IEEE.numeric_std.all;

entity XOR_OP is
    port (
        s0, i0, i1, j0, j1: in std_logic;
        k0, k1, c_out: out std_logic
    );
end entity XOR_OP;

architecture arch of XOR_OP is
begin
    process is begin
        wait on i0, i1, j0, j1;
        k0 <= i0 xor j0;
        k1 <= i1 xor j1;
        c_out <= s0;
    end process;
end architecture arch;

model/alu.vhd
library IEEE;
use IEEE.std_logic_1164.all;
use IEEE.numeric_std.all;

entity alu is
    port (
        s0, s1, s2, i0, i1, j0, j1 : in std_logic;
        k0, k1, c_out : out std_logic
    );
end entity alu;

architecture struc of alu is
    signal k0_XOR, k1_XOR, c_out_XOR, k0_NOT, k1_NOT, c_out_NOT, 
    k0_SUB_2, k1_SUB_2, c_out_SUB_2, k0_INC, k1_INC, c_out_INC: std_logic;
begin
    XOR_OP : entity work.XOR_OP(arch) port map(s0, i0, i1, j0, j1, k0_XOR, k1_XOR, c_out_XOR);
    NOT_OP : entity work.NOT_OP(arch) port map(s0, i0, i1, k0_NOT, k1_NOT, c_out_NOT);
    SUB_2_OP : entity work.SUB_2(arch) port map(s0, s1, i0, i1, j0, j1, k0_SUB_2, k1_SUB_2, c_out_SUB_2);
    INC_OP : entity work.INC(arch) port map(s0, s1, s2, i0, i1, k0_INC, k1_INC, c_out_INC);
    MUX_0 : entity work.MUX(arch) port map(s0, s1, s2, '0', '0', k0_XOR, k0_NOT, '0', '0', k0_SUB_2, k0_INC, k0);
    MUX_1 : entity work.MUX(arch) port map(s0, s1, s2, '0', '0', k1_XOR, k1_NOT, '0', '0', k1_SUB_2, k1_INC, k1);
    MUX_C : entity work.MUX(arch) port map(s0, s1, s2, '0', '0', c_out_XOR, c_out_NOT, '0', '0', c_out_SUB_2, c_out_INC, c_out);
end architecture struc;

model/alu_tb.vhd
library IEEE;
use IEEE.std_logic_1164.all;
use IEEE.numeric_std.all;

entity alu_tb is
end entity alu_tb;

architecture sim of alu_tb is
    signal tS0, tS1, tS2, tI0, tI1, tJ0, tJ1, tK0, tK1, tCout : std_logic;
begin
    uut : entity work.alu(struc)
        port map(tS0, tS1, tS2, tI0, tI1, tJ0, tJ1, tK0, tK1, tCout);
    tester : process is
        variable test_in : unsigned(6 downto 0);
    begin
        test_in := B"0000000";
        for count in 0 to 127 loop
            tS0 <= test_in(6);
            tS1 <= test_in(5);
            tS2 <= test_in(4);
            tI0 <= test_in(3);
            tI1 <= test_in(2);
            tJ0 <= test_in(1);
            tJ1 <= test_in(0);
            wait for 10 ns;

            test_in := test_in + 1;
        end loop;

        wait;
    end process;
end architecture sim;

model/alu.vcd
$date
  Mon Oct  5 17:00:26 2020
$end
$version
  GHDL v0
$end
$timescale
  1 fs
$end
$scope module standard $end
$upscope $end
$scope module std_logic_1164 $end
$upscope $end
$scope module numeric_std $end
$upscope $end
$scope module alu_tb $end
$var reg 1 ! ts0 $end
$var reg 1 " ts1 $end
$var reg 1 # ts2 $end
$var reg 1 $ ti0 $end
$var reg 1 % ti1 $end
$var reg 1 & tj0 $end
$var reg 1 ' tj1 $end
$var reg 1 ( tk0 $end
$var reg 1 ) tk1 $end
$var reg 1 * tcout $end
$scope module uut $end
$var reg 1 + s0 $end
$var reg 1 , s1 $end
$var reg 1 - s2 $end
$var reg 1 . i0 $end
$var reg 1 / i1 $end
$var reg 1 0 j0 $end
$var reg 1 1 j1 $end
$var reg 1 2 k0 $end
$var reg 1 3 k1 $end
$var reg 1 4 c_out $end
$var reg 1 5 k0_xor $end
$var reg 1 6 k1_xor $end
$var reg 1 7 c_out_xor $end
$var reg 1 8 k0_not $end
$var reg 1 9 k1_not $end
$var reg 1 : c_out_not $end
$var reg 1 ; k0_sub_2 $end
$var reg 1 < k1_sub_2 $end
$var reg 1 = c_out_sub_2 $end
$var reg 1 > k0_inc $end
$var reg 1 ? k1_inc $end
$var reg 1 @ c_out_inc $end
$scope module xor_op $end
$var reg 1 A s0 $end
$var reg 1 B i0 $end
$var reg 1 C i1 $end
$var reg 1 D j0 $end
$var reg 1 E j1 $end
$var reg 1 F k0 $end
$var reg 1 G k1 $end
$var reg 1 H c_out $end
$upscope $end
$scope module not_op $end
$var reg 1 I s0 $end
$var reg 1 J i0 $end
$var reg 1 K i1 $end
$var reg 1 L k0 $end
$var reg 1 M k1 $end
$var reg 1 N c_out $end
$upscope $end
$scope module sub_2_op $end
$var reg 1 O s0 $end
$var reg 1 P s1 $end
$var reg 1 Q i0 $end
$var reg 1 R i1 $end
$var reg 1 S j0 $end
$var reg 1 T j1 $end
$var reg 1 U k0 $end
$var reg 1 V k1 $end
$var reg 1 W c_out $end
$var reg 1 X j0_c $end
$var reg 1 Y j1_c $end
$var reg 1 Z s_and $end
$var reg 1 [ c $end
$upscope $end
$scope module inc_op $end
$var reg 1 \ s0 $end
$var reg 1 ] s1 $end
$var reg 1 ^ s2 $end
$var reg 1 _ i0 $end
$var reg 1 ` i1 $end
$var reg 1 a k0 $end
$var reg 1 b k1 $end
$var reg 1 c c_out $end
$var reg 1 d s_and $end
$var reg 1 e c $end
$upscope $end
$scope module mux_0 $end
$var reg 1 f s0 $end
$var reg 1 g s1 $end
$var reg 1 h s2 $end
$var reg 1 i a0 $end
$var reg 1 j a1 $end
$var reg 1 k a2 $end
$var reg 1 l a3 $end
$var reg 1 m a4 $end
$var reg 1 n a5 $end
$var reg 1 o a6 $end
$var reg 1 p a7 $end
$var reg 1 q z $end
$var reg 1 r i0 $end
$var reg 1 s i1 $end
$var reg 1 t i2 $end
$var reg 1 u i3 $end
$var reg 1 v i4 $end
$var reg 1 w i5 $end
$var reg 1 x i6 $end
$var reg 1 y i7 $end
$upscope $end
$scope module mux_1 $end
$var reg 1 z s0 $end
$var reg 1 { s1 $end
$var reg 1 | s2 $end
$var reg 1 } a0 $end
$var reg 1 !" a1 $end
$var reg 1 "" a2 $end
$var reg 1 #" a3 $end
$var reg 1 $" a4 $end
$var reg 1 %" a5 $end
$var reg 1 &" a6 $end
$var reg 1 '" a7 $end
$var reg 1 (" z $end
$var reg 1 )" i0 $end
$var reg 1 *" i1 $end
$var reg 1 +" i2 $end
$var reg 1 ," i3 $end
$var reg 1 -" i4 $end
$var reg 1 ." i5 $end
$var reg 1 /" i6 $end
$var reg 1 0" i7 $end
$upscope $end
$scope module mux_c $end
$var reg 1 1" s0 $end
$var reg 1 2" s1 $end
$var reg 1 3" s2 $end
$var reg 1 4" a0 $end
$var reg 1 5" a1 $end
$var reg 1 6" a2 $end
$var reg 1 7" a3 $end
$var reg 1 8" a4 $end
$var reg 1 9" a5 $end
$var reg 1 :" a6 $end
$var reg 1 ;" a7 $end
$var reg 1 <" z $end
$var reg 1 =" i0 $end
$var reg 1 >" i1 $end
$var reg 1 ?" i2 $end
$var reg 1 @" i3 $end
$var reg 1 A" i4 $end
$var reg 1 B" i5 $end
$var reg 1 C" i6 $end
$var reg 1 D" i7 $end
$upscope $end
$upscope $end
$upscope $end
$enddefinitions $end
#0
0!
0"
0#
0$
0%
0&
0'
0(
0)
0*
0+
0,
0-
0.
0/
00
01
02
03
04
05
06
07
18
19
0:
1;
1<
0=
0>
0?
0@
0A
0B
0C
0D
0E
0F
0G
0H
0I
0J
0K
1L
1M
0N
0O
0P
0Q
0R
0S
0T
1U
1V
0W
1X
1Y
0Z
0[
0\
0]
0^
0_
0`
0a
0b
0c
0d
0e
0f
0g
0h
0i
0j
0k
1l
0m
0n
1o
0p
0q
0r
0s
0t
0u
0v
0w
0x
0y
0z
0{
0|
0}
0!"
0""
1#"
0$"
0%"
1&"
0'"
0("
0)"
0*"
0+"
0,"
0-"
0."
0/"
00"
01"
02"
03"
04"
05"
06"
07"
08"
09"
0:"
0;"
0<"
0="
0>"
0?"
0@"
0A"
0B"
0C"
0D"
#10000000
1'
11
16
0<
1E
1G
1T
0V
0Y
1""
0&"
#20000000
1&
0'
10
01
15
06
0;
1<
1D
0E
1F
0G
1S
0T
0U
1V
0X
1Y
1k
0o
0""
1&"
#30000000
1'
11
16
0<
1E
1G
1T
0V
0Y
1""
0&"
#40000000
1%
0&
0'
1/
00
01
05
09
0;
0<
1=
1?
1C
0D
0E
0F
1K
0M
1R
0S
0T
0U
0V
1W
1X
1Y
1[
1`
1b
0k
0o
0#"
0&"
1'"
1:"
#50000000
1'
11
06
1;
1<
0=
1E
0G
1T
1U
1V
0W
0Y
0[
1o
0""
1&"
0:"
#60000000
1&
0'
10
01
15
16
1;
0<
1D
0E
1F
1G
1S
0T
1U
0V
0X
1Y
1[
1k
1o
1""
0&"
#70000000
1'
11
06
0;
1<
1E
0G
1T
0U
1V
0Y
0[
0o
0""
1&"
#80000000
1$
0%
0&
0'
1.
0/
00
01
08
19
0;
1<
1=
1>
0?
1B
0C
0D
0E
1J
0K
0L
1M
1Q
0R
0S
0T
0U
1V
1W
1X
1Y
1_
0`
1a
0b
0l
0o
1p
1#"
1&"
0'"
1:"
#90000000
1'
11
16
0<
1E
1G
1T
0V
0Y
1""
0&"
#100000000
1&
0'
10
01
05
06
1;
1<
0=
1D
0E
0F
0G
1S
0T
1U
1V
0W
0X
1Y
0k
1o
0""
1&"
0:"
#110000000
1'
11
16
0<
1E
1G
1T
0V
0Y
1""
0&"
#120000000
1%
0&
0'
1/
00
01
15
09
1;
0<
1=
1?
1C
0D
0E
1F
1K
0M
1R
0S
0T
1U
0V
1W
1X
1Y
1[
1`
1b
1k
1o
0#"
0&"
1'"
1:"
#130000000
1'
11
06
0;
1<
1E
0G
1T
0U
1V
0Y
0[
0o
0""
1&"
#140000000
1&
0'
10
01
05
16
0;
0<
1=
1D
0E
0F
1G
1S
0T
0U
0V
1W
0X
1Y
1[
0k
0o
1""
0&"
1:"
#150000000
1'
11
06
1;
1<
0=
1E
0G
1T
1U
1V
0W
0Y
0[
1o
0""
1&"
0:"
#160000000
1#
0$
0%
0&
0'
1-
0.
0/
00
01
18
19
1;
1<
0>
0?
0B
0C
0D
0E
0J
0K
1L
1M
0Q
0R
0S
0T
1U
1V
1X
1Y
1^
0_
0`
0a
0b
1h
1l
1o
0p
1|
1#"
1&"
0'"
13"
#170000000
1'
11
16
0<
1E
1G
1T
0V
0Y
1""
0&"
#180000000
1&
0'
10
01
15
06
0;
1<
1D
0E
1F
0G
1S
0T
0U
1V
0X
1Y
1k
0o
0""
1&"
#190000000
1'
11
16
0<
1E
1G
1T
0V
0Y
1""
0&"
#200000000
1%
0&
0'
1/
00
01
05
09
0;
0<
1=
1?
1C
0D
0E
0F
1K
0M
1R
0S
0T
0U
0V
1W
1X
1Y
1[
1`
1b
0k
0o
0#"
0&"
1'"
1:"
#210000000
1'
11
06
1;
1<
0=
1E
0G
1T
1U
1V
0W
0Y
0[
1o
0""
1&"
0:"
#220000000
1&
0'
10
01
15
16
1;
0<
1D
0E
1F
1G
1S
0T
1U
0V
0X
1Y
1[
1k
1o
1""
0&"
#230000000
1'
11
06
0;
1<
1E
0G
1T
0U
1V
0Y
0[
0o
0""
1&"
#240000000
1$
0%
0&
0'
1.
0/
00
01
08
19
0;
1<
1=
1>
0?
1B
0C
0D
0E
1J
0K
0L
1M
1Q
0R
0S
0T
0U
1V
1W
1X
1Y
1_
0`
1a
0b
0l
0o
1p
1#"
1&"
0'"
1:"
#250000000
1'
11
16
0<
1E
1G
1T
0V
0Y
1""
0&"
#260000000
1&
0'
10
01
05
06
1;
1<
0=
1D
0E
0F
0G
1S
0T
1U
1V
0W
0X
1Y
0k
1o
0""
1&"
0:"
#270000000
1'
11
16
0<
1E
1G
1T
0V
0Y
1""
0&"
#280000000
1%
0&
0'
1/
00
01
15
09
1;
0<
1=
1?
1C
0D
0E
1F
1K
0M
1R
0S
0T
1U
0V
1W
1X
1Y
1[
1`
1b
1k
1o
0#"
0&"
1'"
1:"
#290000000
1'
11
06
0;
1<
1E
0G
1T
0U
1V
0Y
0[
0o
0""
1&"
#300000000
1&
0'
10
01
05
16
0;
0<
1=
1D
0E
0F
1G
1S
0T
0U
0V
1W
0X
1Y
1[
0k
0o
1""
0&"
1:"
#310000000
1'
11
06
1;
1<
0=
1E
0G
1T
1U
1V
0W
0Y
0[
1o
0""
1&"
0:"
#320000000
1"
0#
0$
0%
0&
0'
1,
0-
0.
0/
00
01
18
19
1;
1<
0>
0?
0B
0C
0D
0E
0J
0K
1L
1M
1P
0Q
0R
0S
0T
1U
1V
1X
1Y
1]
0^
0_
0`
0a
0b
1g
0h
1l
1o
0p
1{
0|
1#"
1&"
0'"
12"
03"
#330000000
1'
1)
11
13
16
0<
1E
1G
1T
0V
0Y
1""
0&"
1("
1+"
#340000000
1&
0'
1(
0)
10
01
12
03
15
06
0;
1<
1D
0E
1F
0G
1S
0T
0U
1V
0X
1Y
1k
0o
1q
1t
0""
1&"
0("
0+"
#350000000
1'
1)
11
13
16
0<
1E
1G
1T
0V
0Y
1""
0&"
1("
1+"
#360000000
1%
0&
0'
0(
1/
00
01
02
05
09
0;
0<
1=
1?
1C
0D
0E
0F
1K
0M
1R
0S
0T
0U
0V
1W
1X
1Y
1[
1`
1b
0k
0o
0q
0t
0#"
0&"
1'"
1:"
#370000000
1'
0)
11
03
06
1;
1<
0=
1E
0G
1T
1U
1V
0W
0Y
0[
1o
0""
1&"
0("
0+"
0:"
#380000000
1&
0'
1(
1)
10
01
12
13
15
16
1;
0<
1D
0E
1F
1G
1S
0T
1U
0V
0X
1Y
1[
1k
1o
1q
1t
1""
0&"
1("
1+"
#390000000
1'
0)
11
03
06
0;
1<
1E
0G
1T
0U
1V
0Y
0[
0o
0""
1&"
0("
0+"
#400000000
1$
0%
0&
0'
1.
0/
00
01
08
19
0;
1<
1=
1>
0?
1B
0C
0D
0E
1J
0K
0L
1M
1Q
0R
0S
0T
0U
1V
1W
1X
1Y
1_
0`
1a
0b
0l
0o
1p
1#"
1&"
0'"
1:"
#410000000
1'
1)
11
13
16
0<
1E
1G
1T
0V
0Y
1""
0&"
1("
1+"
#420000000
1&
0'
0(
0)
10
01
02
03
05
06
1;
1<
0=
1D
0E
0F
0G
1S
0T
1U
1V
0W
0X
1Y
0k
1o
0q
0t
0""
1&"
0("
0+"
0:"
#430000000
1'
1)
11
13
16
0<
1E
1G
1T
0V
0Y
1""
0&"
1("
1+"
#440000000
1%
0&
0'
1(
1/
00
01
12
15
09
1;
0<
1=
1?
1C
0D
0E
1F
1K
0M
1R
0S
0T
1U
0V
1W
1X
1Y
1[
1`
1b
1k
1o
1q
1t
0#"
0&"
1'"
1:"
#450000000
1'
0)
11
03
06
0;
1<
1E
0G
1T
0U
1V
0Y
0[
0o
0""
1&"
0("
0+"
#460000000
1&
0'
0(
1)
10
01
02
13
05
16
0;
0<
1=
1D
0E
0F
1G
1S
0T
0U
0V
1W
0X
1Y
1[
0k
0o
0q
0t
1""
0&"
1("
1+"
1:"
#470000000
1'
0)
11
03
06
1;
1<
0=
1E
0G
1T
1U
1V
0W
0Y
0[
1o
0""
1&"
0("
0+"
0:"
#480000000
1#
0$
0%
0&
0'
1(
1)
1-
0.
0/
00
01
12
13
18
19
1;
1<
0>
0?
0B
0C
0D
0E
0J
0K
1L
1M
0Q
0R
0S
0T
1U
1V
1X
1Y
1^
0_
0`
0a
0b
1h
1l
1o
0p
1q
1u
1|
1#"
1&"
0'"
1("
1,"
13"
#490000000
1'
11
16
0<
1E
1G
1T
0V
0Y
1""
0&"
#500000000
1&
0'
10
01
15
06
0;
1<
1D
0E
1F
0G
1S
0T
0U
1V
0X
1Y
1k
0o
0""
1&"
#510000000
1'
11
16
0<
1E
1G
1T
0V
0Y
1""
0&"
#520000000
1%
0&
0'
0)
1/
00
01
03
05
09
0;
0<
1=
1?
1C
0D
0E
0F
1K
0M
1R
0S
0T
0U
0V
1W
1X
1Y
1[
1`
1b
0k
0o
0#"
0&"
1'"
0("
0,"
1:"
#530000000
1'
11
06
1;
1<
0=
1E
0G
1T
1U
1V
0W
0Y
0[
1o
0""
1&"
0:"
#540000000
1&
0'
10
01
15
16
1;
0<
1D
0E
1F
1G
1S
0T
1U
0V
0X
1Y
1[
1k
1o
1""
0&"
#550000000
1'
11
06
0;
1<
1E
0G
1T
0U
1V
0Y
0[
0o
0""
1&"
#560000000
1$
0%
0&
0'
0(
1)
1.
0/
00
01
02
13
08
19
0;
1<
1=
1>
0?
1B
0C
0D
0E
1J
0K
0L
1M
1Q
0R
0S
0T
0U
1V
1W
1X
1Y
1_
0`
1a
0b
0l
0o
1p
0q
0u
1#"
1&"
0'"
1("
1,"
1:"
#570000000
1'
11
16
0<
1E
1G
1T
0V
0Y
1""
0&"
#580000000
1&
0'
10
01
05
06
1;
1<
0=
1D
0E
0F
0G
1S
0T
1U
1V
0W
0X
1Y
0k
1o
0""
1&"
0:"
#590000000
1'
11
16
0<
1E
1G
1T
0V
0Y
1""
0&"
#600000000
1%
0&
0'
0)
1/
00
01
03
15
09
1;
0<
1=
1?
1C
0D
0E
1F
1K
0M
1R
0S
0T
1U
0V
1W
1X
1Y
1[
1`
1b
1k
1o
0#"
0&"
1'"
0("
0,"
1:"
#610000000
1'
11
06
0;
1<
1E
0G
1T
0U
1V
0Y
0[
0o
0""
1&"
#620000000
1&
0'
10
01
05
16
0;
0<
1=
1D
0E
0F
1G
1S
0T
0U
0V
1W
0X
1Y
1[
0k
0o
1""
0&"
1:"
#630000000
1'
11
06
1;
1<
0=
1E
0G
1T
1U
1V
0W
0Y
0[
1o
0""
1&"
0:"
#640000000
1!
0"
0#
0$
0%
0&
0'
1+
0,
0-
0.
0/
00
01
17
18
19
1:
1;
1<
0>
0?
1A
0B
0C
0D
0E
1H
1I
0J
0K
1L
1M
1N
1O
0P
0Q
0R
0S
0T
1U
1V
1X
1Y
1\
0]
0^
0_
0`
0a
0b
1f
0g
0h
1l
1o
0p
1z
0{
0|
1#"
1&"
0'"
11"
02"
03"
16"
17"
#650000000
1'
11
16
0<
1E
1G
1T
0V
0Y
1""
0&"
#660000000
1&
0'
10
01
15
06
0;
1<
1D
0E
1F
0G
1S
0T
0U
1V
0X
1Y
1k
0o
0""
1&"
#670000000
1'
11
16
0<
1E
1G
1T
0V
0Y
1""
0&"
#680000000
1%
0&
0'
1/
00
01
05
09
0;
0<
1=
1?
1C
0D
0E
0F
1K
0M
1R
0S
0T
0U
0V
1W
1X
1Y
1[
1`
1b
0k
0o
0#"
0&"
1'"
1:"
#690000000
1'
11
06
1;
1<
0=
1E
0G
1T
1U
1V
0W
0Y
0[
1o
0""
1&"
0:"
#700000000
1&
0'
10
01
15
16
1;
0<
1D
0E
1F
1G
1S
0T
1U
0V
0X
1Y
1[
1k
1o
1""
0&"
#710000000
1'
11
06
0;
1<
1E
0G
1T
0U
1V
0Y
0[
0o
0""
1&"
#720000000
1$
0%
0&
0'
1.
0/
00
01
08
19
0;
1<
1=
1>
0?
1B
0C
0D
0E
1J
0K
0L
1M
1Q
0R
0S
0T
0U
1V
1W
1X
1Y
1_
0`
1a
0b
0l
0o
1p
1#"
1&"
0'"
1:"
#730000000
1'
11
16
0<
1E
1G
1T
0V
0Y
1""
0&"
#740000000
1&
0'
10
01
05
06
1;
1<
0=
1D
0E
0F
0G
1S
0T
1U
1V
0W
0X
1Y
0k
1o
0""
1&"
0:"
#750000000
1'
11
16
0<
1E
1G
1T
0V
0Y
1""
0&"
#760000000
1%
0&
0'
1/
00
01
15
09
1;
0<
1=
1?
1C
0D
0E
1F
1K
0M
1R
0S
0T
1U
0V
1W
1X
1Y
1[
1`
1b
1k
1o
0#"
0&"
1'"
1:"
#770000000
1'
11
06
0;
1<
1E
0G
1T
0U
1V
0Y
0[
0o
0""
1&"
#780000000
1&
0'
10
01
05
16
0;
0<
1=
1D
0E
0F
1G
1S
0T
0U
0V
1W
0X
1Y
1[
0k
0o
1""
0&"
1:"
#790000000
1'
11
06
1;
1<
0=
1E
0G
1T
1U
1V
0W
0Y
0[
1o
0""
1&"
0:"
#800000000
1#
0$
0%
0&
0'
1-
0.
0/
00
01
18
19
1;
1<
0>
0?
0B
0C
0D
0E
0J
0K
1L
1M
0Q
0R
0S
0T
1U
1V
1X
1Y
1^
0_
0`
0a
0b
1h
1l
1o
0p
1|
1#"
1&"
0'"
13"
#810000000
1'
11
16
0<
1E
1G
1T
0V
0Y
1""
0&"
#820000000
1&
0'
10
01
15
06
0;
1<
1D
0E
1F
0G
1S
0T
0U
1V
0X
1Y
1k
0o
0""
1&"
#830000000
1'
11
16
0<
1E
1G
1T
0V
0Y
1""
0&"
#840000000
1%
0&
0'
1/
00
01
05
09
0;
0<
1=
1?
1C
0D
0E
0F
1K
0M
1R
0S
0T
0U
0V
1W
1X
1Y
1[
1`
1b
0k
0o
0#"
0&"
1'"
1:"
#850000000
1'
11
06
1;
1<
0=
1E
0G
1T
1U
1V
0W
0Y
0[
1o
0""
1&"
0:"
#860000000
1&
0'
10
01
15
16
1;
0<
1D
0E
1F
1G
1S
0T
1U
0V
0X
1Y
1[
1k
1o
1""
0&"
#870000000
1'
11
06
0;
1<
1E
0G
1T
0U
1V
0Y
0[
0o
0""
1&"
#880000000
1$
0%
0&
0'
1.
0/
00
01
08
19
0;
1<
1=
1>
0?
1B
0C
0D
0E
1J
0K
0L
1M
1Q
0R
0S
0T
0U
1V
1W
1X
1Y
1_
0`
1a
0b
0l
0o
1p
1#"
1&"
0'"
1:"
#890000000
1'
11
16
0<
1E
1G
1T
0V
0Y
1""
0&"
#900000000
1&
0'
10
01
05
06
1;
1<
0=
1D
0E
0F
0G
1S
0T
1U
1V
0W
0X
1Y
0k
1o
0""
1&"
0:"
#910000000
1'
11
16
0<
1E
1G
1T
0V
0Y
1""
0&"
#920000000
1%
0&
0'
1/
00
01
15
09
1;
0<
1=
1?
1C
0D
0E
1F
1K
0M
1R
0S
0T
1U
0V
1W
1X
1Y
1[
1`
1b
1k
1o
0#"
0&"
1'"
1:"
#930000000
1'
11
06
0;
1<
1E
0G
1T
0U
1V
0Y
0[
0o
0""
1&"
#940000000
1&
0'
10
01
05
16
0;
0<
1=
1D
0E
0F
1G
1S
0T
0U
0V
1W
0X
1Y
1[
0k
0o
1""
0&"
1:"
#950000000
1'
11
06
1;
1<
0=
1E
0G
1T
1U
1V
0W
0Y
0[
1o
0""
1&"
0:"
#960000000
1"
0#
0$
0%
0&
0'
0(
0)
1*
1,
0-
0.
0/
00
01
02
03
14
18
19
0;
0<
1=
0>
0?
0B
0C
0D
0E
0J
0K
1L
1M
1P
0Q
0R
0S
0T
0U
0V
1W
1X
1Y
1Z
1[
1]
0^
0_
0`
0a
0b
1g
0h
1l
0o
0p
0q
0x
1{
0|
1#"
0&"
0'"
0("
0/"
12"
03"
1:"
1<"
1C"
#970000000
1'
1(
1)
0*
11
12
13
04
16
1;
1<
0=
1E
1G
1T
1U
1V
0W
0Y
0[
1o
1q
1x
1""
1&"
1("
1/"
0:"
0<"
0C"
#980000000
1&
0'
1(
0)
10
01
12
03
15
06
1;
0<
1D
0E
1F
0G
1S
0T
1U
0V
0X
1Y
1[
1k
1o
1q
1x
0""
0&"
0("
0/"
#990000000
1'
0(
1)
11
02
13
16
0;
1<
1E
1G
1T
0U
1V
0Y
0[
0o
0q
0x
1""
1&"
1("
1/"
#1000000000
1%
0&
0'
1)
1*
1/
00
01
13
14
05
09
1<
1=
1?
1C
0D
0E
0F
1K
0M
1R
0S
0T
1V
1W
1X
1Y
1[
1`
1b
0k
0#"
1&"
1'"
1("
1/"
1:"
1<"
1C"
#1010000000
1'
0)
11
03
06
0<
1E
0G
1T
0V
0Y
0""
0&"
0("
0/"
#1020000000
1&
0'
1(
1)
0*
10
01
12
13
04
15
16
1;
1<
0=
1D
0E
1F
1G
1S
0T
1U
1V
0W
0X
1Y
1k
1o
1q
1x
1""
1&"
1("
1/"
0:"
0<"
0C"
#1030000000
1'
0)
11
03
06
0<
1E
0G
1T
0V
0Y
0""
0&"
0("
0/"
#1040000000
1$
0%
0&
0'
1(
0)
1*
1.
0/
00
01
12
03
14
08
19
1;
0<
1=
1>
0?
1B
0C
0D
0E
1J
0K
0L
1M
1Q
0R
0S
0T
1U
0V
1W
1X
1Y
1[
1_
0`
1a
0b
0l
1o
1p
1q
1x
1#"
0&"
0'"
0("
0/"
1:"
1<"
1C"
#1050000000
1'
0(
1)
11
02
13
16
0;
1<
1E
1G
1T
0U
1V
0Y
0[
0o
0q
0x
1""
1&"
1("
1/"
#1060000000
1&
0'
0(
0)
1*
10
01
02
03
14
05
06
0;
0<
1=
1D
0E
0F
0G
1S
0T
0U
0V
1W
0X
1Y
1[
0k
0o
0q
0x
0""
0&"
0("
0/"
1:"
1<"
1C"
#1070000000
1'
1(
1)
0*
11
12
13
04
16
1;
1<
0=
1E
1G
1T
1U
1V
0W
0Y
0[
1o
1q
1x
1""
1&"
1("
1/"
0:"
0<"
0C"
#1080000000
1%
0&
0'
1)
1*
1/
00
01
13
14
15
09
1<
1=
1?
1C
0D
0E
1F
1K
0M
1R
0S
0T
1V
1W
1X
1Y
1[
1`
1b
1k
0#"
1&"
1'"
1("
1/"
1:"
1<"
1C"
#1090000000
1'
0)
11
03
06
0<
1E
0G
1T
0V
0Y
0""
0&"
0("
0/"
#1100000000
1&
0'
0(
1)
10
01
02
13
05
16
0;
1<
1D
0E
0F
1G
1S
0T
0U
1V
0X
1Y
0k
0o
0q
0x
1""
1&"
1("
1/"
#1110000000
1'
0)
11
03
06
0<
1E
0G
1T
0V
0Y
0""
0&"
0("
0/"
#1120000000
1#
0$
0%
0&
0'
0(
1)
0*
1-
0.
0/
00
01
02
13
04
18
19
0;
0<
1=
0>
1?
0B
0C
0D
0E
0J
0K
1L
1M
0Q
0R
0S
0T
0U
0V
1W
1X
1Y
1[
1^
0_
0`
0a
1b
1d
1h
1l
0o
0p
0q
0y
1|
1#"
0&"
1'"
1("
10"
13"
1:"
0<"
0C"
#1130000000
1'
11
16
1;
1<
0=
1E
1G
1T
1U
1V
0W
0Y
0[
1o
1""
1&"
0:"
#1140000000
1&
0'
10
01
15
06
1;
0<
1D
0E
1F
0G
1S
0T
1U
0V
0X
1Y
1[
1k
1o
0""
0&"
#1150000000
1'
11
16
0;
1<
1E
1G
1T
0U
1V
0Y
0[
0o
1""
1&"
#1160000000
1%
0&
0'
1(
0)
1/
00
01
12
03
05
09
1<
1=
1>
0?
1C
0D
0E
0F
1K
0M
1R
0S
0T
1V
1W
1X
1Y
1[
1`
1a
0b
1e
0k
1p
1q
1y
0#"
1&"
0'"
0("
00"
1:"
#1170000000
1'
11
06
0<
1E
0G
1T
0V
0Y
0""
0&"
#1180000000
1&
0'
10
01
15
16
1;
1<
0=
1D
0E
1F
1G
1S
0T
1U
1V
0W
0X
1Y
1k
1o
1""
1&"
0:"
#1190000000
1'
11
06
0<
1E
0G
1T
0V
0Y
0""
0&"
