model/mux.vhd
library IEEE;
use IEEE.std_logic_1164.all;
use IEEE.numeric_std.all;

-- 8 to 1 multiplexer
entity MUX is
    port (
        s0, s1, s2, i0, i1, i2, i3, i4, i5, i6, i7 : in std_logic;
        z : out std_logic
    );
end entity MUX;

architecture arch of MUX is
    signal a0, a1, a2, a3, a4, a5, a6, a7 : std_logic;
begin
    process is begin
        wait on s0, s1, s2, a0, a1, a2, a3, a4, a5, a6, a7, i0, i1, i2, i3, i4, i5, i6, i7 ;
        a0 <= i0  and (not s0)  and  (not s1)  and  (not s2);
        a1 <= i1  and (not s0)  and  (not s1)  and       s2;             
        a2 <= i2  and (not s0)  and       s1   and  (not s2);
        a3 <= i3  and (not s0)  and       s1   and       s2;
        a4 <= i4  and      s0   and  (not s1)  and  (not s2);
        a5 <= i5  and      s0   and  (not s1)  and       s2;
        a6 <= i6  and      s0   and       s1   and  (not s2);
        a7 <= i7  and      s0   and       s1   and       s2;
        z <= a0 or a1 or a2 or a3 or a4 or a5 or a6 or a7;
    end process;
end architecture arch;

model/inc.vhd
library IEEE;
use IEEE.std_logic_1164.all;
use IEEE.numeric_std.all;

entity INC is
    port (
        s0, s1, s2, i0, i1 : in std_logic;
        k0, k1, c_out : out std_logic
    );
end entity INC;

architecture arch of INC is
    signal s_and, c : std_logic;
begin
    process is begin
        wait on s0, s1, s2, i0, i1, s_and, c;
        s_and <= s0 and s1 and s2;
        k1 <= s_and xor i1;
        c <= s_and and i1;
        k0 <= i0 xor c;
        c_out <= c and i0;
    end process;    
end architecture arch;

model/sub_2.vhd
library IEEE;
use IEEE.std_logic_1164.all;
use IEEE.numeric_std.all;

-- SUB 2's operation
entity SUB_2 is
    port (
        s0, s1, i0, i1, j0, j1 : in std_logic;
        k0, k1, c_out : out std_logic
    );
end entity SUB_2;

architecture arch of SUB_2 is
    signal j0_c, j1_c, s_and, c : std_logic;
begin
    process is begin
        wait on s0, s1, i0, i1, j0, j1, j0_c, j1_c, c;
        j1_c <= not j1;
        j0_c <= not j0;
        s_and <= s0 and s1;

        k1 <= (i1 xor j1_c) xor s_and;
        c <= (i1 and j1_c) or (s_and and (i1 xor j1_c));
        k0 <= (i0 xor j0_c) xor c;
        c_out <= (i0 and j0_c) or (c and (i0 xor j0_c));
    end process;
end architecture arch;

model/sub_1.vhd
library IEEE;
use IEEE.std_logic_1164.all;

-- SUB 1's operation
entity SUB_1 is
	port (
		i0, j0, i1, j1 : in std_logic;
		k0, k1, c_out : out std_logic
	) ;
end entity SUB_1; 

architecture arch of SUB_1 is
	signal j0_c, j1_c, carry: std_logic;
begin
	process is begin
		wait on i0, j0, i1, j1, j0_c, j1_c, carry;
		j1_c <= not j1;
		j0_c <= not j0;

		k1 <= i1 xor j1_c;
		carry <= i1 and j1_c;
		k0 <= (i0 xor j0_c) xor carry;
		c_out <= (i0 and j0_c) or (carry and (i0 xor j0_c));

	end process;
end architecture arch;

model/add.vhd
library IEEE;
use IEEE.std_logic_1164.all;

-- ADD operation
entity ADD is
	port (
		i0, j0, i1, j1 : in std_logic;
		k0, k1, c_out : out std_logic
	) ;
end entity ADD; 

architecture arch of ADD is
	signal carry: std_logic;
begin
	process is begin
		wait on i0, j0, i1, j1, carry;
		k1 <= i1 xor j1;
		carry <= i1 and j1;
		k0 <= (i0 xor j0) xor carry;
		c_out <= (i0 and j0) or (carry and (i0 xor j0));
	end process;
end architecture arch;

model/not.vhd
library IEEE;
use IEEE.std_logic_1164.all;
use IEEE.numeric_std.all;

-- NOT operaton
entity NOT_OP is
    port (
        s0, i0, i1 : in std_logic;
        k0, k1, c_out: out std_logic
    );
end entity NOT_OP;

architecture arch of NOT_OP is
begin
    process is begin
        wait on i0, i1;
        k0 <= not i0;
        k1 <= not i1;
        c_out <= s0;
    end process;
end architecture arch;

model/xor.vhd
library IEEE;
use IEEE.std_logic_1164.all;
use IEEE.numeric_std.all;

-- XOR operation
entity XOR_OP is
    port (
        s0, i0, i1, j0, j1: in std_logic;
        k0, k1, c_out: out std_logic
    );
end entity XOR_OP;

architecture arch of XOR_OP is
begin
    process is begin
        wait on i0, i1, j0, j1;
        k0 <= i0 xor j0;
        k1 <= i1 xor j1;
        c_out <= s0;
    end process;
end architecture arch;

model/or.vhd
library IEEE;
use IEEE.std_logic_1164.all;

-- OR operation
entity OR_OP is
	port (
		i0, j0, i1, j1, s0 : in std_logic;
		k0, k1, c_out : out std_logic
	);
end entity OR_OP; 

architecture arch of OR_OP is
begin
	process is begin
		wait on i0, j0, i1, j1, s0;
		k1 <= i1 or j1;
		k0 <= i0 or j0;
		c_out <= s0;
	end process;
end architecture arch;

model/and.vhd
library IEEE;
use IEEE.std_logic_1164.all;

-- AND operation
entity AND_OP is
	port (
		i0, j0, i1, j1, s0 : in std_logic;
		k0, k1, c_out : out std_logic
	);
end entity AND_OP; 

architecture arch of AND_OP is
begin
	process is begin
		wait on i0, j0, i1, j1, s0;
		k1 <= i1 and j1;
		k0 <= i0 and j0;
		c_out <= s0;
	end process;
end architecture arch;

model/alu.vhd
library IEEE;
use IEEE.std_logic_1164.all;
use IEEE.numeric_std.all;

-- alu entity 
entity alu is
    port (
        s0, s1, s2, i0, i1, j0, j1 : in std_logic;
        k0, k1, c_out : out std_logic
    );
end entity alu;

-- stuctural implementation 
architecture struc of alu is
    -- signals used as output and carry for each operation
    signal k0_AND, k1_AND, c_out_AND, 
    k0_OR, k1_OR, c_out_OR, 
    k0_XOR, k1_XOR, c_out_XOR, 
    k0_NOT, k1_NOT, c_out_NOT, 
    k0_ADD, k1_ADD, c_out_ADD, 
    k0_SUB_1, k1_SUB_1, c_out_SUB_1, 
    k0_SUB_2, k1_SUB_2, c_out_SUB_2, 
    k0_INC, k1_INC, c_out_INC: std_logic;
begin
    -- operations
    AND_OP : entity work.AND_OP(arch) port map (i0, j0, i1, j1, s0, k0_AND, k1_AND, c_out_AND);
    OR_OP : entity work.OR_OP(arch) port map (i0, j0, i1, j1, s0, k0_OR, k1_OR, c_out_OR);
    XOR_OP : entity work.XOR_OP(arch) port map(s0, i0, i1, j0, j1, k0_XOR, k1_XOR, c_out_XOR);
    NOT_OP : entity work.NOT_OP(arch) port map(s0, i0, i1, k0_NOT, k1_NOT, c_out_NOT);
    ADD : entity work.ADD(arch) port map (i0, j0, i1, j1, k0_ADD, k1_ADD, c_out_ADD);
    SUB_1 : entity work.SUB_1(arch) port map (i0, j0, i1, j1, k0_SUB_1, k1_SUB_1, c_out_SUB_1);
    SUB_2_OP : entity work.SUB_2(arch) port map(s0, s1, i0, i1, j0, j1, k0_SUB_2, k1_SUB_2, c_out_SUB_2);
    INC_OP : entity work.INC(arch) port map(s0, s1, s2, i0, i1, k0_INC, k1_INC, c_out_INC);

    -- 8 to 1 mux for k0, k1, and c_out
    MUX_0 : entity work.MUX(arch) port map(s0, s1, s2, k0_AND, k0_OR, k0_XOR, k0_NOT, k0_ADD, k0_SUB_1, k0_SUB_2, k0_INC, k0);
    MUX_1 : entity work.MUX(arch) port map(s0, s1, s2, k1_AND, k1_OR, k1_XOR, k1_NOT, k1_ADD, k1_SUB_1, k1_SUB_2, k1_INC, k1);
    MUX_C : entity work.MUX(arch) port map(s0, s1, s2, c_out_AND, c_out_OR, c_out_XOR, c_out_NOT, c_out_ADD, c_out_SUB_1, c_out_SUB_2, c_out_INC, c_out);
end architecture struc;

test/and_tb.vhd
library IEEE;
use IEEE.std_logic_1164.all;
use IEEE.numeric_std.all;

-- test bench for AND operaton
entity and_tb is
end entity and_tb;

architecture sim of and_tb is
    signal tS0, tS1, tS2, tI0, tI1, tJ0, tJ1, tK0, tK1, tCout : std_logic;
begin
    uut : entity work.alu(struc)
        port map(tS0, tS1, tS2, tI0, tI1, tJ0, tJ1, tK0, tK1, tCout);
    tester : process is
        variable test_in : unsigned(3 downto 0);
        variable error_count : integer := 0;
        variable output_0, output_1, output_c : std_logic;
    begin
        test_in := B"0000"; -- initialize

        -- selectors for operation AND
        tS0 <= '0';
        tS1 <= '0';
        tS2 <= '0';

        -- loop for testing
        for count in 0 to 15 loop
            tI0 <= test_in(3);
            tI1 <= test_in(2);
            tJ0 <= test_in(1);
            tJ1 <= test_in(0);
            wait for 10 ns;

            -- generate expected outputs
            output_0 := tI0 and tJ0;
            output_1 := tI1 and tJ1;
            output_c := '0';
            assert(output_0=tK0 and output_1=tK1 and output_c=tCout) report "AND Gate error!" severity error;

            if (output_0/=tK0 or output_1/=tK1 or output_c/=tCout) then error_count := error_count + 1; end if;

            test_in := test_in + 1;
        end loop;

        report "Done with AND operation test. There were " & integer'image(error_count) & " errors.";
        -- report the number of errors encountered

        wait;
    end process;
end architecture sim;

test/and_tb.vcd
$date
  Mon Oct  5 20:20:14 2020
$end
$version
  GHDL v0
$end
$timescale
  1 fs
$end
$scope module standard $end
$upscope $end
$scope module std_logic_1164 $end
$upscope $end
$scope module numeric_std $end
$upscope $end
$scope module and_tb $end
$var reg 1 ! ts0 $end
$var reg 1 " ts1 $end
$var reg 1 # ts2 $end
$var reg 1 $ ti0 $end
$var reg 1 % ti1 $end
$var reg 1 & tj0 $end
$var reg 1 ' tj1 $end
$var reg 1 ( tk0 $end
$var reg 1 ) tk1 $end
$var reg 1 * tcout $end
$scope module uut $end
$var reg 1 + s0 $end
$var reg 1 , s1 $end
$var reg 1 - s2 $end
$var reg 1 . i0 $end
$var reg 1 / i1 $end
$var reg 1 0 j0 $end
$var reg 1 1 j1 $end
$var reg 1 2 k0 $end
$var reg 1 3 k1 $end
$var reg 1 4 c_out $end
$var reg 1 5 k0_and $end
$var reg 1 6 k1_and $end
$var reg 1 7 c_out_and $end
$var reg 1 8 k0_or $end
$var reg 1 9 k1_or $end
$var reg 1 : c_out_or $end
$var reg 1 ; k0_xor $end
$var reg 1 < k1_xor $end
$var reg 1 = c_out_xor $end
$var reg 1 > k0_not $end
$var reg 1 ? k1_not $end
$var reg 1 @ c_out_not $end
$var reg 1 A k0_add $end
$var reg 1 B k1_add $end
$var reg 1 C c_out_add $end
$var reg 1 D k0_sub_1 $end
$var reg 1 E k1_sub_1 $end
$var reg 1 F c_out_sub_1 $end
$var reg 1 G k0_sub_2 $end
$var reg 1 H k1_sub_2 $end
$var reg 1 I c_out_sub_2 $end
$var reg 1 J k0_inc $end
$var reg 1 K k1_inc $end
$var reg 1 L c_out_inc $end
$scope module and_op $end
$var reg 1 M i0 $end
$var reg 1 N j0 $end
$var reg 1 O i1 $end
$var reg 1 P j1 $end
$var reg 1 Q s0 $end
$var reg 1 R k0 $end
$var reg 1 S k1 $end
$var reg 1 T c_out $end
$upscope $end
$scope module or_op $end
$var reg 1 U i0 $end
$var reg 1 V j0 $end
$var reg 1 W i1 $end
$var reg 1 X j1 $end
$var reg 1 Y s0 $end
$var reg 1 Z k0 $end
$var reg 1 [ k1 $end
$var reg 1 \ c_out $end
$upscope $end
$scope module xor_op $end
$var reg 1 ] s0 $end
$var reg 1 ^ i0 $end
$var reg 1 _ i1 $end
$var reg 1 ` j0 $end
$var reg 1 a j1 $end
$var reg 1 b k0 $end
$var reg 1 c k1 $end
$var reg 1 d c_out $end
$upscope $end
$scope module not_op $end
$var reg 1 e s0 $end
$var reg 1 f i0 $end
$var reg 1 g i1 $end
$var reg 1 h k0 $end
$var reg 1 i k1 $end
$var reg 1 j c_out $end
$upscope $end
$scope module add $end
$var reg 1 k i0 $end
$var reg 1 l j0 $end
$var reg 1 m i1 $end
$var reg 1 n j1 $end
$var reg 1 o k0 $end
$var reg 1 p k1 $end
$var reg 1 q c_out $end
$var reg 1 r carry $end
$upscope $end
$scope module sub_1 $end
$var reg 1 s i0 $end
$var reg 1 t j0 $end
$var reg 1 u i1 $end
$var reg 1 v j1 $end
$var reg 1 w k0 $end
$var reg 1 x k1 $end
$var reg 1 y c_out $end
$var reg 1 z j0_c $end
$var reg 1 { j1_c $end
$var reg 1 | carry $end
$upscope $end
$scope module sub_2_op $end
$var reg 1 } s0 $end
$var reg 1 !" s1 $end
$var reg 1 "" i0 $end
$var reg 1 #" i1 $end
$var reg 1 $" j0 $end
$var reg 1 %" j1 $end
$var reg 1 &" k0 $end
$var reg 1 '" k1 $end
$var reg 1 (" c_out $end
$var reg 1 )" j0_c $end
$var reg 1 *" j1_c $end
$var reg 1 +" s_and $end
$var reg 1 ," c $end
$upscope $end
$scope module inc_op $end
$var reg 1 -" s0 $end
$var reg 1 ." s1 $end
$var reg 1 /" s2 $end
$var reg 1 0" i0 $end
$var reg 1 1" i1 $end
$var reg 1 2" k0 $end
$var reg 1 3" k1 $end
$var reg 1 4" c_out $end
$var reg 1 5" s_and $end
$var reg 1 6" c $end
$upscope $end
$scope module mux_0 $end
$var reg 1 7" s0 $end
$var reg 1 8" s1 $end
$var reg 1 9" s2 $end
$var reg 1 :" i0 $end
$var reg 1 ;" i1 $end
$var reg 1 <" i2 $end
$var reg 1 =" i3 $end
$var reg 1 >" i4 $end
$var reg 1 ?" i5 $end
$var reg 1 @" i6 $end
$var reg 1 A" i7 $end
$var reg 1 B" z $end
$var reg 1 C" a0 $end
$var reg 1 D" a1 $end
$var reg 1 E" a2 $end
$var reg 1 F" a3 $end
$var reg 1 G" a4 $end
$var reg 1 H" a5 $end
$var reg 1 I" a6 $end
$var reg 1 J" a7 $end
$upscope $end
$scope module mux_1 $end
$var reg 1 K" s0 $end
$var reg 1 L" s1 $end
$var reg 1 M" s2 $end
$var reg 1 N" i0 $end
$var reg 1 O" i1 $end
$var reg 1 P" i2 $end
$var reg 1 Q" i3 $end
$var reg 1 R" i4 $end
$var reg 1 S" i5 $end
$var reg 1 T" i6 $end
$var reg 1 U" i7 $end
$var reg 1 V" z $end
$var reg 1 W" a0 $end
$var reg 1 X" a1 $end
$var reg 1 Y" a2 $end
$var reg 1 Z" a3 $end
$var reg 1 [" a4 $end
$var reg 1 \" a5 $end
$var reg 1 ]" a6 $end
$var reg 1 ^" a7 $end
$upscope $end
$scope module mux_c $end
$var reg 1 _" s0 $end
$var reg 1 `" s1 $end
$var reg 1 a" s2 $end
$var reg 1 b" i0 $end
$var reg 1 c" i1 $end
$var reg 1 d" i2 $end
$var reg 1 e" i3 $end
$var reg 1 f" i4 $end
$var reg 1 g" i5 $end
$var reg 1 h" i6 $end
$var reg 1 i" i7 $end
$var reg 1 j" z $end
$var reg 1 k" a0 $end
$var reg 1 l" a1 $end
$var reg 1 m" a2 $end
$var reg 1 n" a3 $end
$var reg 1 o" a4 $end
$var reg 1 p" a5 $end
$var reg 1 q" a6 $end
$var reg 1 r" a7 $end
$upscope $end
$upscope $end
$upscope $end
$enddefinitions $end
#0
0!
0"
0#
0$
0%
0&
0'
0(
0)
0*
0+
0,
0-
0.
0/
00
01
02
03
04
05
06
07
08
09
0:
0;
0<
0=
1>
1?
0@
0A
0B
0C
1D
1E
0F
1G
1H
0I
0J
0K
0L
0M
0N
0O
0P
0Q
0R
0S
0T
0U
0V
0W
0X
0Y
0Z
0[
0\
0]
0^
0_
0`
0a
0b
0c
0d
0e
0f
0g
1h
1i
0j
0k
0l
0m
0n
0o
0p
0q
0r
0s
0t
0u
0v
1w
1x
0y
1z
1{
0|
0}
0!"
0""
0#"
0$"
0%"
1&"
1'"
0("
1)"
1*"
0+"
0,"
0-"
0."
0/"
00"
01"
02"
03"
04"
05"
06"
07"
08"
09"
0:"
0;"
0<"
1="
0>"
1?"
1@"
0A"
0B"
0C"
0D"
0E"
0F"
0G"
0H"
0I"
0J"
0K"
0L"
0M"
0N"
0O"
0P"
1Q"
0R"
1S"
1T"
0U"
0V"
0W"
0X"
0Y"
0Z"
0["
0\"
0]"
0^"
0_"
0`"
0a"
0b"
0c"
0d"
0e"
0f"
0g"
0h"
0i"
0j"
0k"
0l"
0m"
0n"
0o"
0p"
0q"
0r"
#10000000
1'
11
19
1<
1B
0E
0H
1P
1X
1[
1a
1c
1n
1p
1v
0x
0{
1%"
0'"
0*"
1O"
1P"
1R"
0S"
0T"
#20000000
1&
0'
10
01
18
09
1;
0<
1A
0B
0D
1E
0G
1H
1N
0P
1V
0X
1Z
0[
1`
0a
1b
0c
1l
0n
1o
0p
1t
0v
0w
1x
0z
1{
1$"
0%"
0&"
1'"
0)"
1*"
1;"
1<"
1>"
0?"
0@"
0O"
0P"
0R"
1S"
1T"
#30000000
1'
11
19
1<
1B
0E
0H
1P
1X
1[
1a
1c
1n
1p
1v
0x
0{
1%"
0'"
0*"
1O"
1P"
1R"
0S"
0T"
#40000000
1%
0&
0'
1/
00
01
08
0;
0?
0A
0D
0E
1F
0G
0H
1I
1K
0N
1O
0P
0V
1W
0X
0Z
1_
0`
0a
0b
1g
0i
0l
1m
0n
0o
0t
1u
0v
0w
0x
1y
1z
1{
1|
1#"
0$"
0%"
0&"
0'"
1("
1)"
1*"
1,"
11"
13"
0;"
0<"
0>"
0?"
0@"
0Q"
0S"
0T"
1U"
1g"
1h"
#50000000
1'
1)
11
13
16
0<
1A
0B
1D
1E
0F
1G
1H
0I
1P
1S
1X
1a
0c
1n
1o
0p
1r
1v
1w
1x
0y
0{
0|
1%"
1&"
1'"
0("
0*"
0,"
1>"
1?"
1@"
1N"
0P"
0R"
1S"
1T"
1V"
1W"
0g"
0h"
#60000000
1&
0'
0)
10
01
03
06
18
1;
1<
1A
1B
0C
1D
0E
1G
0H
1N
0P
0S
1V
0X
1Z
1`
0a
1b
1c
1l
0n
1o
1p
0q
0r
1t
0v
1w
0x
0z
1{
1|
1$"
0%"
1&"
0'"
0)"
1*"
1,"
1;"
1<"
1>"
1?"
1@"
0N"
1P"
1R"
0S"
0T"
0V"
0W"
0f"
#70000000
1'
1)
11
13
16
0<
0A
0B
1C
0D
1E
0G
1H
1P
1S
1X
1a
0c
1n
0o
0p
1q
1r
1v
0w
1x
0{
0|
1%"
0&"
1'"
0*"
0,"
0>"
0?"
0@"
1N"
0P"
0R"
1S"
1T"
1V"
1W"
1f"
#80000000
1$
0%
0&
0'
0)
1.
0/
00
01
03
06
09
0>
1?
1A
0C
0D
1E
1F
0G
1H
1I
1J
0K
1M
0N
0O
0P
0S
1U
0V
0W
0X
0[
1^
0_
0`
0a
1f
0g
0h
1i
1k
0l
0m
0n
1o
0q
0r
1s
0t
0u
0v
0w
1x
1y
1z
1{
1""
0#"
0$"
0%"
0&"
1'"
1("
1)"
1*"
10"
01"
12"
03"
0="
1>"
0?"
0@"
1A"
0N"
0O"
1Q"
1S"
1T"
0U"
0V"
0W"
0f"
1g"
1h"
#90000000
1'
11
19
1<
1B
0E
0H
1P
1X
1[
1a
1c
1n
1p
1v
0x
0{
1%"
0'"
0*"
1O"
1P"
1R"
0S"
0T"
#100000000
1&
0'
1(
10
01
12
15
09
0;
0<
0A
0B
1C
1D
1E
0F
1G
1H
0I
1N
0P
1R
1V
0X
0[
1`
0a
0b
0c
1l
0n
0o
0p
1q
1t
0v
1w
1x
0y
0z
1{
1$"
0%"
1&"
1'"
0("
0)"
1*"
1:"
0<"
0>"
1?"
1@"
1B"
1C"
0O"
0P"
0R"
1S"
1T"
1f"
0g"
0h"
#110000000
1'
11
19
1<
1B
0E
0H
1P
1X
1[
1a
1c
1n
1p
1v
0x
0{
1%"
0'"
0*"
1O"
1P"
1R"
0S"
0T"
#120000000
1%
0&
0'
0(
1/
00
01
02
05
1;
0?
1A
0C
1D
0E
1F
1G
0H
1I
1K
0N
1O
0P
0R
0V
1W
0X
1_
0`
0a
1b
1g
0i
0l
1m
0n
1o
0q
0t
1u
0v
1w
0x
1y
1z
1{
1|
1#"
0$"
0%"
1&"
0'"
1("
1)"
1*"
1,"
11"
13"
0:"
1<"
1>"
1?"
1@"
0B"
0C"
0Q"
0S"
0T"
1U"
0f"
1g"
1h"
#130000000
1'
1)
11
13
16
0<
0A
0B
1C
0D
1E
0G
1H
1P
1S
1X
1a
0c
1n
0o
0p
1q
1r
1v
0w
1x
0{
0|
1%"
0&"
1'"
0*"
0,"
0>"
0?"
0@"
1N"
0P"
0R"
1S"
1T"
1V"
1W"
1f"
#140000000
1&
0'
1(
0)
10
01
12
03
15
06
0;
1<
0A
1B
0D
0E
1F
0G
0H
1I
1N
0P
1R
0S
1V
0X
1`
0a
0b
1c
1l
0n
0o
1p
0r
1t
0v
0w
0x
1y
0z
1{
1|
1$"
0%"
0&"
0'"
1("
0)"
1*"
1,"
1:"
0<"
0>"
0?"
0@"
1B"
1C"
0N"
1P"
1R"
0S"
0T"
0V"
0W"
1g"
1h"
#150000000
1'
1)
11
13
16
0<
1A
0B
1D
1E
0F
1G
1H
0I
1P
1S
1X
1a
0c
1n
1o
0p
1r
1v
1w
1x
0y
0{
0|
1%"
1&"
1'"
0("
0*"
0,"
1>"
1?"
1@"
1N"
0P"
0R"
1S"
1T"
1V"
1W"
0g"
0h"
